basic_type_operations/README.md
basic_type_operations/__init__.py
basic_type_operations/date_operation.py
basic_type_operations/dict_operation.py
basic_type_operations/list_operation.py
basic_type_operations/number_operation.py
basic_type_operations/str_operation.py
basic_type_operations/tuple_operation.py
basic_type_operations-0.1.1.dist-info/LICENSE
basic_type_operations-0.1.1.dist-info/METADATA
basic_type_operations-0.1.1.dist-info/WHEEL
basic_type_operations-0.1.1.dist-info/top_level.txt
basic_type_operations-0.1.1.dist-info/RECORD
