Metadata-Version: 2.1
Name: basic-type-operations
Version: 0.1.1
Summary: Short description
Home-page: https://gitee.com/SkyOceanchen/basic_type_operations.git
Author: SkyOceanChen
Author-email: skyoceanchen@foxmail.com
Maintainer: SkyOceanChen
Maintainer-email: skyoceanchen@foxmail.com
License: MIT
Classifier: Development Status :: 3 - Alpha
Classifier: Intended Audience :: Developers
Classifier: Operating System :: OS Independent
Classifier: Topic :: Software Development :: Build Tools
Classifier: License :: OSI Approved :: MIT License
Classifier: Programming Language :: Python :: 3.6
Classifier: Programming Language :: Python :: 3.8
Classifier: Programming Language :: Python :: 3.10
License-File: LICENSE
Requires-Dist: numpy
Requires-Dist: extra-utils
Requires-Dist: munch
Requires-Dist: fuzzywuzzy
Requires-Dist: python-Levenshtein
Requires-Dist: pinyin
Requires-Dist: djangorestframework
